socketio_pg_manager/__init__.py
socketio_pg_manager/async_pg_manager.py
socketio_pg_manager-0.0.5.dist-info/LICENSE.txt
socketio_pg_manager-0.0.5.dist-info/METADATA
socketio_pg_manager-0.0.5.dist-info/WHEEL
socketio_pg_manager-0.0.5.dist-info/top_level.txt
socketio_pg_manager-0.0.5.dist-info/RECORD
