Metadata-Version: 2.1
Name: socketio_pg_manager
Version: 0.0.5
Summary: Postgres client manager for python-socketio
Author-email: Chenyu Wang <wangchenyu2017@gmail.com>
Project-URL: Homepage, https://github.com/MonoidDev/socketio_pg_manager
Project-URL: Bug Tracker, https://github.com/MonoidDev/socketio_pg_manager/issues
Classifier: Environment :: Web Environment
Classifier: Intended Audience :: Developers
Classifier: Programming Language :: Python :: 3
Classifier: License :: OSI Approved :: MIT License
Classifier: Operating System :: OS Independent
Requires-Python: >=3.11
License-File: LICENSE.txt
Requires-Dist: python-socketio >=5.11.0
Requires-Dist: psycopg[binary] >=3.1.17
Requires-Dist: psycopg-pool >=3.2.3
